read_env_keys/__init__.py
read_env_keys/read_env_keys.py
read_env_keys-0.0.3.dist-info/METADATA
read_env_keys-0.0.3.dist-info/WHEEL
read_env_keys-0.0.3.dist-info/licenses/LICENSE
read_env_keys-0.0.3.dist-info/RECORD
