Metadata-Version: 2.1
Name: read_env_keys
Version: 0.0.3
Summary: A small package to easily read API keys from env files
Project-URL: Homepage, https://github.com/MidpriceDog/read-env
Project-URL: Bug Tracker, https://github.com/MidpriceDog/read-env/issues
Author: MidpriceDog
License-File: LICENSE
Classifier: License :: OSI Approved :: MIT License
Classifier: Operating System :: OS Independent
Classifier: Programming Language :: Python :: 3
Requires-Python: >=3.7
